{
  "bootstrap-sha": "d12757fe8f44f5cf2bb9092c686d642fe41f436f",
  "packages": {
    ".": {
      "release-type": "ruby",
      "package-name": "process_executer",
      "changelog-path": "CHANGELOG.md",
      "version-file": "lib/process_executer/version.rb",
      "bump-minor-pre-major": true,
      "bump-patch-for-minor-pre-major": true,
      "draft": false,
      "prerelease": false,
      "include-component-in-tag": false
    }
  },
  "plugins": [
    {
      "type": "sentence-case"
    }
  ],
  "$schema": "https://raw.githubusercontent.com/googleapis/release-please/main/schemas/config.json"
}
